nonebot_plugin_nai3_bot/__init__.py
nonebot_plugin_nai3_bot/config.py
nonebot_plugin_nai3_bot/platfrom/__init__.py
nonebot_plugin_nai3_bot/platfrom/nai4.py
nonebot_plugin_nai3_bot/platfrom/novelai.py
nonebot_plugin_nai3_bot/platfrom/stable_diffusion.py
nonebot_plugin_nai3_bot/random_tag.py
nonebot_plugin_nai3_bot/tags.json
nonebot_plugin_nai3_bot/tags1.json
nonebot_plugin_nai3_bot-1.4.0.dist-info/METADATA
nonebot_plugin_nai3_bot-1.4.0.dist-info/WHEEL
nonebot_plugin_nai3_bot-1.4.0.dist-info/RECORD
