Metadata-Version: 2.1
Name: nonebot-plugin-nai3-bot
Version: 1.4.0
Summary: 基于GPT4+NovelAI V3/V4,Bot在将自然语言转换为NAI3/NAI4提示词并绘图发送的同时，还会以自定义人格和你聊天。同时支持随机画风和随机同人图生成。
License: MIT
Author: Alpaca
Author-email: admin@alpaca.kim
Requires-Python: >=3.8,<4.0
Classifier: License :: OSI Approved :: MIT License
Classifier: Programming Language :: Python :: 3
Classifier: Programming Language :: Python :: 3.8
Classifier: Programming Language :: Python :: 3.9
Classifier: Programming Language :: Python :: 3.10
Classifier: Programming Language :: Python :: 3.11
Classifier: Programming Language :: Python :: 3.12
Classifier: Programming Language :: Python :: 3.13
Requires-Dist: Pillow (>=9.1.0,<10.0.0)
Requires-Dist: httpx (>=0.27.0,<0.28.0)
Requires-Dist: nonebot-adapter-onebot (>=2.2.1,<3.0.0)
Requires-Dist: nonebot2 (>=2.0.0rc3,<3.0.0)
Requires-Dist: numpy (>=1.25.2,<2.0.0)
Requires-Dist: openai (>=1.30.1,<2.0.0)
